{
  "project_info": {
    "project_number": "416551071780",
    "firebase_url": "https://myshoppy-d10ff.firebaseio.com",
    "project_id": "myshoppy-d10ff",
    "storage_bucket": "myshoppy-d10ff.appspot.com"
  },
  "client": [
    {
      "client_info": {
        "mobilesdk_app_id": "1:416551071780:android:48d3c06f66f25a017428b1",
        "android_client_info": {
          "package_name": "com.e.myshoppy"
        }
      },
      "oauth_client": [
        {
          "client_id": "416551071780-d5tanhv77e2i07lvhovmejel322mj23q.apps.googleusercontent.com",
          "client_type": 3
        }
      ],
      "api_key": [
        {
          "current_key": "AIzaSyAnWFwRKRg6UDe3ePP6k8Gmhs9nBicd-lI"
        }
      ],
      "services": {
        "appinvite_service": {
          "other_platform_oauth_client": [
            {
              "client_id": "416551071780-d5tanhv77e2i07lvhovmejel322mj23q.apps.googleusercontent.com",
              "client_type": 3
            }
          ]
        }
      }
    }
  ],
  "configuration_version": "1"
}